[{"time": 1.4, "text": "Can we just be honest?", "words": [{"word": "Can", "start": 1.4, "end": 2.34}, {"word": "we", "start": 2.34, "end": 3.14}, {"word": "just", "start": 3.18, "end": 4.78}, {"word": "be", "start": 5.08, "end": 5.88}, {"word": "honest?", "start": 7.24, "end": 9.09}]}, {"time": 9.74, "text": "These are the requirements", "words": [{"word": "These", "start": 9.74, "end": 9.93}, {"word": "are", "start": 9.94, "end": 10.5}, {"word": "the", "start": 10.5, "end": 11.64}, {"word": "requirements", "start": 11.64, "end": 15.22, "stretch": true}]}, {"time": 15.53, "text": "If you think you can be my one and only true love", "words": [{"word": "If", "start": 15.53, "end": 16.25}, {"word": "you", "start": 16.25, "end": 16.91}, {"word": "think", "start": 16.91, "end": 17.71}, {"word": "you", "start": 17.71, "end": 18.51}, {"word": "can", "start": 18.51, "end": 19.23}, {"word": "be", "start": 19.23, "end": 19.95}, {"word": "my", "start": 19.95, "end": 20.71}, {"word": "one", "start": 20.71, "end": 21.43}, {"word": "and", "start": 21.43, "end": 22.37}, {"word": "only", "start": 22.37, "end": 23.47}, {"word": "true", "start": 23.47, "end": 24.83}, {"word": "love", "start": 27.45, "end": 29.05, "stretch": true}]}, {"time": 29.94, "text": "You must promise to love me", "words": [{"word": "You", "start": 29.94, "end": 30.64}, {"word": "must", "start": 30.64, "end": 31.88}, {"word": "promise", "start": 31.88, "end": 33.22}, {"word": "to", "start": 33.22, "end": 34.02}, {"word": "love", "start": 34.34, "end": 35.52}, {"word": "me", "start": 35.52, "end": 35.87}]}, {"time": 35.92, "text": "And damn it, if you fuck me over", "words": [{"word": "And", "start": 35.92, "end": 36.84}, {"word": "damn", "start": 36.84, "end": 37.32}, {"word": "it,", "start": 37.32, "end": 37.74}, {"word": "if", "start": 37.74, "end": 38.18}, {"word": "you", "start": 38.18, "end": 38.92}, {"word": "fuck", "start": 38.92, "end": 39.72}, {"word": "me", "start": 39.72, "end": 40.42}, {"word": "over", "start": 41.64, "end": 43.24, "stretch": true}]}, {"time": 43.38, "text": "I will rip your fuckin' face apart", "words": [{"word": "I", "start": 43.38, "end": 43.88}, {"word": "will", "start": 44.2, "end": 44.78}, {"word": "rip", "start": 44.78, "end": 45.44}, {"word": "your", "start": 45.44, "end": 46.44}, {"word": "fuckin'", "start": 46.44, "end": 48.48}, {"word": "face", "start": 48.48, "end": 50.08}, {"word": "apart", "start": 51.46, "end": 52.56}]}, {"type": "vocal_cue", "time": 52.86, "end": 63.14}, {"time": 63.96, "text": "Step one", "words": [{"word": "Step", "start": 63.96, "end": 64.74}, {"word": "one", "start": 65.16, "end": 65.26}]}, {"time": 65.31, "text": "You must accept that I'm a little out my mind", "words": [{"word": "You", "start": 65.31, "end": 65.33}, {"word": "must", "start": 65.33, "end": 65.67}, {"word": "accept", "start": 65.67, "end": 66.35}, {"word": "that", "start": 66.35, "end": 66.75}, {"word": "I'm", "start": 66.75, "end": 67.27}, {"word": "a", "start": 67.27, "end": 67.37}, {"word": "little", "start": 67.37, "end": 67.79}, {"word": "out", "start": 67.79, "end": 68.19}, {"word": "my", "start": 68.19, "end": 68.41}, {"word": "mind", "start": 68.41, "end": 68.51, "stretch": true}]}, {"time": 68.56, "text": "Step two", "words": [{"word": "Step", "start": 68.56, "end": 68.78}, {"word": "two", "start": 68.78, "end": 69.749, "stretch": true}]}, {"time": 69.799, "text": "This is a waste if you can't walk me down the finish line", "words": [{"word": "This", "start": 69.799, "end": 70.439}, {"word": "is", "start": 70.439, "end": 70.579}, {"word": "a", "start": 70.579, "end": 70.879}, {"word": "waste", "start": 70.879, "end": 71.139}, {"word": "if", "start": 71.139, "end": 71.439}, {"word": "you", "start": 71.439, "end": 71.979}, {"word": "can't", "start": 71.979, "end": 72.119}, {"word": "walk", "start": 72.119, "end": 72.479}, {"word": "me", "start": 72.479, "end": 72.859}, {"word": "down", "start": 72.859, "end": 73.139}, {"word": "the", "start": 73.139, "end": 73.419}, {"word": "finish", "start": 73.419, "end": 73.959}, {"word": "line", "start": 73.959, "end": 74.059}]}, {"time": 74.109, "text": "Step three", "words": [{"word": "Step", "start": 74.109, "end": 74.649}, {"word": "three", "start": 74.649, "end": 75.399, "stretch": true}]}, {"time": 75.449, "text": "Give me passion, don't make fun of my fashion", "words": [{"word": "Give", "start": 75.449, "end": 75.949}, {"word": "me", "start": 76.249, "end": 76.349}, {"word": "passion,", "start": 76.349, "end": 76.749}, {"word": "don't", "start": 76.749, "end": 77.669}, {"word": "make", "start": 77.669, "end": 78.309}, {"word": "fun", "start": 78.309, "end": 78.589}, {"word": "of", "start": 78.589, "end": 78.869}, {"word": "my", "start": 78.869, "end": 79.309}, {"word": "fashion", "start": 79.309, "end": 80.029, "stretch": true}]}, {"time": 80.079, "text": "Step four", "words": [{"word": "Step", "start": 80.079, "end": 80.659}, {"word": "four", "start": 80.659, "end": 80.969}]}, {"time": 81.019, "text": "Give me more, give me more, more", "words": [{"word": "Give", "start": 81.019, "end": 81.539}, {"word": "me", "start": 81.899, "end": 82.019}, {"word": "more,", "start": 82.019, "end": 82.379}, {"word": "give", "start": 82.379, "end": 82.659}, {"word": "me", "start": 82.699, "end": 82.979}, {"word": "more,", "start": 82.979, "end": 83.359}, {"word": "more", "start": 83.359, "end": 84.63, "stretch": true}]}, {"time": 84.68, "text": "If you can't handle a heart like mine", "words": [{"word": "If", "start": 84.68, "end": 85.18}, {"word": "you", "start": 85.26, "end": 85.46}, {"word": "can't", "start": 85.46, "end": 85.8}, {"word": "handle", "start": 85.8, "end": 86.44}, {"word": "a", "start": 86.44, "end": 86.94}, {"word": "heart", "start": 87.18, "end": 87.36}, {"word": "like", "start": 87.36, "end": 87.76}, {"word": "mine", "start": 87.76, "end": 88.38, "stretch": true}]}, {"time": 88.43, "text": "Don't waste your time with me", "words": [{"word": "Don't", "start": 88.43, "end": 89.25}, {"word": "waste", "start": 89.25, "end": 89.47}, {"word": "your", "start": 89.47, "end": 89.85}, {"word": "time", "start": 89.85, "end": 90.27}, {"word": "with", "start": 90.27, "end": 90.59}, {"word": "me", "start": 90.59, "end": 91.04, "stretch": true}]}, {"time": 91.09, "text": "If you're not down to bleed, no, oh", "words": [{"word": "If", "start": 91.09, "end": 91.59}, {"word": "you're", "start": 91.59, "end": 92.19}, {"word": "not", "start": 92.19, "end": 92.61}, {"word": "down", "start": 92.61, "end": 92.87}, {"word": "to", "start": 92.87, "end": 93.31}, {"word": "bleed,", "start": 93.31, "end": 93.61}, {"word": "no,", "start": 93.61, "end": 94.29}, {"word": "oh", "start": 95.29, "end": 95.84, "stretch": true}]}, {"time": 95.89, "text": "If you can't handle the chokin', the bitin'", "words": [{"word": "If", "start": 95.89, "end": 96.17}, {"word": "you", "start": 96.17, "end": 96.55}, {"word": "can't", "start": 96.55, "end": 97.33}, {"word": "handle", "start": 97.33, "end": 97.77}, {"word": "the", "start": 97.77, "end": 97.99}, {"word": "chokin',", "start": 97.99, "end": 98.25}, {"word": "the", "start": 98.25, "end": 98.45}, {"word": "bitin'", "start": 98.45, "end": 98.72}]}, {"time": 98.77, "text": "The lovin', the smotherin'", "words": [{"word": "The", "start": 98.77, "end": 98.97}, {"word": "lovin',", "start": 98.97, "end": 99.15}, {"word": "the", "start": 99.15, "end": 99.45}, {"word": "smotherin'", "start": 99.45, "end": 100.7, "stretch": true}]}, {"time": 100.75, "text": "'Til you can't handle it no more, no more", "words": [{"word": "'Til", "start": 100.75, "end": 101.05}, {"word": "you", "start": 101.05, "end": 101.41}, {"word": "can't", "start": 101.41, "end": 101.69}, {"word": "handle", "start": 101.69, "end": 102.17}, {"word": "it", "start": 102.17, "end": 102.39}, {"word": "no", "start": 102.39, "end": 102.77}, {"word": "more,", "start": 102.77, "end": 103.59}, {"word": "no", "start": 103.59, "end": 104.09}, {"word": "more", "start": 104.11, "end": 105.424, "stretch": true}]}, {"time": 105.474, "text": "Go home", "words": [{"word": "Go", "start": 105.474, "end": 106.234}, {"word": "home", "start": 106.234, "end": 108.204, "stretch": true}]}, {"time": 108.254, "text": "Can we just be honest?", "words": [{"word": "Can", "start": 108.254, "end": 108.654}, {"word": "we", "start": 108.654, "end": 109.014}, {"word": "just", "start": 109.014, "end": 109.354}, {"word": "be", "start": 109.354, "end": 109.861}, {"word": "honest?", "start": 110.034, "end": 110.744, "stretch": true}]}, {"time": 110.794, "text": "These are the requirements", "words": [{"word": "These", "start": 110.794, "end": 111.254}, {"word": "are", "start": 111.254, "end": 111.614}, {"word": "the", "start": 111.614, "end": 112.054}, {"word": "requirements", "start": 112.054, "end": 113.184, "stretch": true}]}, {"time": 113.234, "text": "If you think you can be my one and only true love", "words": [{"word": "If", "start": 113.234, "end": 113.773}, {"word": "you", "start": 113.954, "end": 114.274}, {"word": "think", "start": 114.274, "end": 114.514}, {"word": "you", "start": 114.514, "end": 114.834}, {"word": "can", "start": 114.834, "end": 115.174}, {"word": "be", "start": 115.174, "end": 115.554}, {"word": "my", "start": 115.554, "end": 115.914}, {"word": "one", "start": 115.914, "end": 116.134}, {"word": "and", "start": 116.134, "end": 116.594}, {"word": "only", "start": 116.594, "end": 117.014}, {"word": "true", "start": 117.014, "end": 117.554}, {"word": "love", "start": 117.554, "end": 118.444, "stretch": true}]}, {"time": 118.494, "text": "You must promise to love me", "words": [{"word": "You", "start": 118.494, "end": 118.994}, {"word": "must", "start": 118.994, "end": 119.274}, {"word": "promise", "start": 119.274, "end": 119.814}, {"word": "to", "start": 119.814, "end": 120.314}, {"word": "love", "start": 120.394, "end": 120.614}, {"word": "me", "start": 120.614, "end": 121.114, "stretch": true}]}, {"time": 121.164, "text": "And damn it, if you fuck me over", "words": [{"word": "And", "start": 121.164, "end": 121.324}, {"word": "damn", "start": 121.324, "end": 121.844}, {"word": "it,", "start": 121.844, "end": 122.244}, {"word": "if", "start": 122.244, "end": 122.524}, {"word": "you", "start": 122.524, "end": 122.824}, {"word": "fuck", "start": 122.824, "end": 123.064}, {"word": "me", "start": 123.064, "end": 123.504}, {"word": "over", "start": 123.504, "end": 124.678, "stretch": true}]}, {"time": 124.728, "text": "I will rip your fuckin' face apart", "words": [{"word": "I", "start": 124.728, "end": 125.128}, {"word": "will", "start": 125.128, "end": 125.428}, {"word": "rip", "start": 125.428, "end": 125.728}, {"word": "your", "start": 125.728, "end": 126.088}, {"word": "fuckin'", "start": 126.088, "end": 126.568}, {"word": "face", "start": 126.568, "end": 127.508}, {"word": "apart", "start": 127.508, "end": 129.233, "stretch": true}]}, {"time": 129.283, "text": "High school sweethearts, line up", "words": [{"word": "High", "start": 129.283, "end": 129.923}, {"word": "school", "start": 129.923, "end": 130.343}, {"word": "sweethearts,", "start": 130.343, "end": 131.643}, {"word": "line", "start": 131.643, "end": 132.183}, {"word": "up", "start": 132.183, "end": 132.683, "stretch": true}]}, {"time": 132.733, "text": "Not tryna waste my time", "words": [{"word": "Not", "start": 132.733, "end": 133.133}, {"word": "tryna", "start": 133.133, "end": 133.373}, {"word": "waste", "start": 133.373, "end": 133.733}, {"word": "my", "start": 133.733, "end": 134.113}, {"word": "time", "start": 134.113, "end": 134.453}]}, {"time": 134.503, "text": "High school sweethearts, shut up", "words": [{"word": "High", "start": 134.503, "end": 134.943}, {"word": "school", "start": 134.943, "end": 135.363}, {"word": "sweethearts,", "start": 135.363, "end": 135.723}, {"word": "shut", "start": 135.723, "end": 136.706}, {"word": "up", "start": 137.403, "end": 137.903, "stretch": true}]}, {"time": 137.953, "text": "If you're not my type", "words": [{"word": "If", "start": 137.953, "end": 138.273}, {"word": "you're", "start": 138.273, "end": 138.493}, {"word": "not", "start": 138.493, "end": 138.773}, {"word": "my", "start": 138.773, "end": 139.153}, {"word": "type", "start": 139.153, "end": 139.413}]}, {"time": 139.463, "text": "High school sweethearts, line up", "words": [{"word": "High", "start": 139.463, "end": 139.803}, {"word": "school", "start": 139.803, "end": 140.263}, {"word": "sweethearts,", "start": 140.263, "end": 140.643}, {"word": "line", "start": 140.643, "end": 141.543}, {"word": "up", "start": 142.363, "end": 142.863, "stretch": true}]}, {"time": 142.913, "text": "Not tryna waste my time", "words": [{"word": "Not", "start": 142.913, "end": 143.51}, {"word": "tryna", "start": 143.573, "end": 143.893}, {"word": "waste", "start": 143.893, "end": 144.193}, {"word": "my", "start": 144.193, "end": 144.553}, {"word": "time", "start": 144.553, "end": 145.113, "stretch": true}]}, {"time": 145.163, "text": "High school sweethearts, shut up", "words": [{"word": "High", "start": 145.163, "end": 145.623}, {"word": "school", "start": 145.623, "end": 146.043}, {"word": "sweethearts,", "start": 146.043, "end": 146.403}, {"word": "shut", "start": 146.403, "end": 147.446}, {"word": "up", "start": 147.903, "end": 148.424, "stretch": true}]}, {"time": 148.474, "text": "If you're not my type", "words": [{"word": "If", "start": 148.474, "end": 148.774}, {"word": "you're", "start": 148.774, "end": 148.954}, {"word": "not", "start": 148.954, "end": 149.294}, {"word": "my", "start": 149.294, "end": 149.654}, {"word": "type", "start": 149.654, "end": 150.384, "stretch": true}]}, {"time": 150.434, "text": "Step five", "words": [{"word": "Step", "start": 150.434, "end": 151.054}, {"word": "five", "start": 151.054, "end": 151.814, "stretch": true}]}, {"time": 151.864, "text": "You can't be scared to show me off and hold my hand", "words": [{"word": "You", "start": 151.864, "end": 152.044}, {"word": "can't", "start": 152.044, "end": 152.384}, {"word": "be", "start": 152.384, "end": 152.804}, {"word": "scared", "start": 152.804, "end": 153.084}, {"word": "to", "start": 153.084, "end": 153.424}, {"word": "show", "start": 153.424, "end": 153.724}, {"word": "me", "start": 153.724, "end": 154.084}, {"word": "off", "start": 154.084, "end": 154.284}, {"word": "and", "start": 154.284, "end": 154.684}, {"word": "hold", "start": 154.684, "end": 154.884}, {"word": "my", "start": 154.884, "end": 155.364}, {"word": "hand", "start": 155.364, "end": 155.464}]}, {"time": 155.514, "text": "Step six", "words": [{"word": "Step", "start": 155.514, "end": 155.714}, {"word": "six", "start": 155.714, "end": 156.863, "stretch": true}]}, {"time": 156.913, "text": "If you can't put in work, I don't know what you think this fuckin' is", "words": [{"word": "If", "start": 156.913, "end": 157.353}, {"word": "you", "start": 157.353, "end": 157.573}, {"word": "can't", "start": 157.573, "end": 157.793}, {"word": "put", "start": 157.793, "end": 158.173}, {"word": "in", "start": 158.173, "end": 158.373}, {"word": "work,", "start": 158.373, "end": 158.593}, {"word": "I", "start": 158.593, "end": 158.853}, {"word": "don't", "start": 158.853, "end": 159.173}, {"word": "know", "start": 159.173, "end": 159.393}, {"word": "what", "start": 159.393, "end": 159.493}, {"word": "you", "start": 159.493, "end": 159.753}, {"word": "think", "start": 159.753, "end": 160.053}, {"word": "this", "start": 160.053, "end": 160.233}, {"word": "fuckin'", "start": 160.233, "end": 160.573}, {"word": "is", "start": 160.573, "end": 161.073, "stretch": true}]}, {"time": 161.123, "text": "Step seven, this one goes to eleven", "words": [{"word": "Step", "start": 161.123, "end": 161.663}, {"word": "seven,", "start": 161.663, "end": 162.083}, {"word": "this", "start": 162.083, "end": 163.023}, {"word": "one", "start": 163.303, "end": 163.483}, {"word": "goes", "start": 163.483, "end": 163.703}, {"word": "to", "start": 163.703, "end": 164.023}, {"word": "eleven", "start": 164.023, "end": 166.423, "stretch": true}]}, {"time": 166.473, "text": "If you cheat, you will die, die", "words": [{"word": "If", "start": 166.473, "end": 166.833}, {"word": "you", "start": 166.833, "end": 167.093}, {"word": "cheat,", "start": 167.093, "end": 167.333}, {"word": "you", "start": 167.333, "end": 167.853}, {"word": "will", "start": 167.853, "end": 168.773}, {"word": "die,", "start": 169.133, "end": 169.673}, {"word": "die", "start": 169.673, "end": 169.873}]}, {"time": 169.923, "text": "If you can't handle a heart like mine", "words": [{"word": "If", "start": 169.923, "end": 170.323}, {"word": "you", "start": 170.323, "end": 170.523}, {"word": "can't", "start": 170.523, "end": 170.843}, {"word": "handle", "start": 170.843, "end": 171.583}, {"word": "a", "start": 171.583, "end": 172.083}, {"word": "heart", "start": 172.203, "end": 172.383}, {"word": "like", "start": 172.383, "end": 172.803}, {"word": "mine", "start": 172.803, "end": 173.613, "stretch": true}]}, {"time": 173.663, "text": "Don't waste your time with me", "words": [{"word": "Don't", "start": 173.663, "end": 174.463}, {"word": "waste", "start": 174.463, "end": 174.663}, {"word": "your", "start": 174.663, "end": 175.003}, {"word": "time", "start": 175.003, "end": 175.463}, {"word": "with", "start": 175.463, "end": 175.763}, {"word": "me", "start": 175.763, "end": 176.263, "stretch": true}]}, {"time": 176.313, "text": "If you're not down to bleed, no, oh", "words": [{"word": "If", "start": 176.313, "end": 176.913}, {"word": "you're", "start": 176.913, "end": 177.293}, {"word": "not", "start": 177.293, "end": 177.593}, {"word": "down", "start": 177.593, "end": 178.033}, {"word": "to", "start": 178.033, "end": 178.333}, {"word": "bleed,", "start": 178.333, "end": 178.833}, {"word": "no,", "start": 179.893, "end": 179.993}, {"word": "oh", "start": 179.993, "end": 180.619, "stretch": true}]}, {"time": 180.669, "text": "If you can't handle the chokin', the bitin'", "words": [{"word": "If", "start": 180.669, "end": 180.949}, {"word": "you", "start": 180.949, "end": 181.289}, {"word": "can't", "start": 181.289, "end": 182.022}, {"word": "handle", "start": 182.049, "end": 182.509}, {"word": "the", "start": 182.509, "end": 182.749}, {"word": "chokin',", "start": 182.749, "end": 183.009}, {"word": "the", "start": 183.009, "end": 183.189}, {"word": "bitin'", "start": 183.189, "end": 183.289}]}, {"time": 183.339, "text": "The lovin', the smotherin'", "words": [{"word": "The", "start": 183.339, "end": 183.599}, {"word": "lovin',", "start": 183.599, "end": 183.779}, {"word": "the", "start": 183.779, "end": 183.979}, {"word": "smotherin'", "start": 183.979, "end": 185.309, "stretch": true}]}, {"time": 185.359, "text": "'Til you can't handle it no more, no more", "words": [{"word": "'Til", "start": 185.359, "end": 185.599}, {"word": "you", "start": 185.599, "end": 185.839}, {"word": "can't", "start": 185.839, "end": 186.239}, {"word": "handle", "start": 186.239, "end": 186.519}, {"word": "it", "start": 186.519, "end": 186.999}, {"word": "no", "start": 186.999, "end": 187.199}, {"word": "more,", "start": 187.199, "end": 187.619}, {"word": "no", "start": 187.619, "end": 188.293}, {"word": "more", "start": 188.419, "end": 189.767, "stretch": true}]}, {"time": 189.817, "text": "Go home", "words": [{"word": "Go", "start": 189.817, "end": 190.617}, {"word": "home", "start": 190.617, "end": 192.367, "stretch": true}]}, {"time": 192.417, "text": "Can we just be honest?", "words": [{"word": "Can", "start": 192.417, "end": 192.817}, {"word": "we", "start": 192.817, "end": 193.177}, {"word": "just", "start": 193.177, "end": 193.517}, {"word": "be", "start": 193.517, "end": 194.017}, {"word": "honest?", "start": 194.277, "end": 194.647, "stretch": true}]}, {"time": 194.697, "text": "These are the requirements", "words": [{"word": "These", "start": 194.697, "end": 195.297}, {"word": "are", "start": 195.457, "end": 195.917}, {"word": "the", "start": 195.917, "end": 196.297}, {"word": "requirements", "start": 196.297, "end": 197.677, "stretch": true}]}, {"time": 197.727, "text": "If you think you can be my one and only true love", "words": [{"word": "If", "start": 197.727, "end": 198.294}, {"word": "you", "start": 198.447, "end": 198.767}, {"word": "think", "start": 198.767, "end": 199.007}, {"word": "you", "start": 199.007, "end": 199.307}, {"word": "can", "start": 199.307, "end": 199.687}, {"word": "be", "start": 199.687, "end": 200.067}, {"word": "my", "start": 200.067, "end": 200.387}, {"word": "one", "start": 200.387, "end": 200.627}, {"word": "and", "start": 200.627, "end": 201.107}, {"word": "only", "start": 201.107, "end": 201.547}, {"word": "true", "start": 201.547, "end": 202.027}, {"word": "love", "start": 202.027, "end": 203.037, "stretch": true}]}, {"time": 203.087, "text": "You must promise to love me", "words": [{"word": "You", "start": 203.087, "end": 203.547}, {"word": "must", "start": 203.547, "end": 203.887}, {"word": "promise", "start": 203.887, "end": 204.327}, {"word": "to", "start": 204.327, "end": 204.667}, {"word": "love", "start": 204.667, "end": 205.327}, {"word": "me", "start": 205.327, "end": 205.677}]}, {"time": 205.727, "text": "And damn it, if you fuck me over", "words": [{"word": "And", "start": 205.727, "end": 206.267}, {"word": "damn", "start": 206.267, "end": 206.667}, {"word": "it,", "start": 206.667, "end": 206.967}, {"word": "if", "start": 206.967, "end": 207.347}, {"word": "you", "start": 207.347, "end": 207.527}, {"word": "fuck", "start": 207.527, "end": 207.967}, {"word": "me", "start": 207.967, "end": 208.347}, {"word": "over", "start": 208.347, "end": 209.432, "stretch": true}]}, {"time": 209.482, "text": "I will rip your fuckin' face apart", "words": [{"word": "I", "start": 209.482, "end": 209.982}, {"word": "will", "start": 210.022, "end": 210.462}, {"word": "rip", "start": 210.462, "end": 210.722}, {"word": "your", "start": 210.722, "end": 211.022}, {"word": "fuckin'", "start": 211.022, "end": 211.422}, {"word": "face", "start": 211.422, "end": 211.862}, {"word": "apart", "start": 211.862, "end": 213.758, "stretch": true}]}, {"time": 213.808, "text": "High school sweethearts, line up", "words": [{"word": "High", "start": 213.808, "end": 214.468}, {"word": "school", "start": 214.468, "end": 214.848}, {"word": "sweethearts,", "start": 214.848, "end": 216.168}, {"word": "line", "start": 216.168, "end": 216.728}, {"word": "up", "start": 216.728, "end": 217.088}]}, {"time": 217.138, "text": "Not tryna waste my time", "words": [{"word": "Not", "start": 217.138, "end": 217.643}, {"word": "tryna", "start": 217.738, "end": 218.138}, {"word": "waste", "start": 218.138, "end": 218.398}, {"word": "my", "start": 218.398, "end": 218.758}, {"word": "time", "start": 218.758, "end": 219.098, "stretch": true}]}, {"time": 219.148, "text": "High school sweethearts, shut up", "words": [{"word": "High", "start": 219.148, "end": 219.528}, {"word": "school", "start": 219.528, "end": 219.968}, {"word": "sweethearts,", "start": 219.968, "end": 220.388}, {"word": "shut", "start": 220.388, "end": 220.748}, {"word": "up", "start": 220.748, "end": 221.314, "stretch": true}]}, {"time": 221.364, "text": "If you're not my type", "words": [{"word": "If", "start": 221.364, "end": 221.844}, {"word": "you're", "start": 221.844, "end": 222.124}, {"word": "not", "start": 222.124, "end": 222.364}, {"word": "my", "start": 222.364, "end": 222.724}, {"word": "type", "start": 222.724, "end": 222.834}]}, {"time": 222.884, "text": "High school sweethearts, line up", "words": [{"word": "High", "start": 222.884, "end": 223.244}, {"word": "school", "start": 223.244, "end": 223.584}, {"word": "sweethearts,", "start": 223.584, "end": 224.064}, {"word": "line", "start": 224.064, "end": 224.404}, {"word": "up", "start": 224.404, "end": 224.904, "stretch": true}]}, {"time": 224.954, "text": "Not tryna waste my time", "words": [{"word": "Not", "start": 224.954, "end": 225.456}, {"word": "tryna", "start": 225.574, "end": 225.914}, {"word": "waste", "start": 225.914, "end": 226.194}, {"word": "my", "start": 226.194, "end": 226.594}, {"word": "time", "start": 226.594, "end": 227.034, "stretch": true}]}, {"time": 227.084, "text": "High school sweethearts, shut up", "words": [{"word": "High", "start": 227.084, "end": 227.424}, {"word": "school", "start": 227.424, "end": 227.864}, {"word": "sweethearts,", "start": 227.864, "end": 228.304}, {"word": "shut", "start": 228.304, "end": 228.624}, {"word": "up", "start": 228.624, "end": 229.201, "stretch": true}]}, {"time": 229.98, "text": "If you're not my type", "words": [{"word": "If", "start": 229.98, "end": 230.32}, {"word": "you're", "start": 230.32, "end": 230.5}, {"word": "not", "start": 230.5, "end": 230.82}, {"word": "my", "start": 230.82, "end": 231.2}, {"word": "type", "start": 231.2, "end": 232.433, "stretch": true}]}, {"time": 232.58, "text": "Could you hold me through the night?", "words": [{"word": "Could", "start": 232.58, "end": 233.28}, {"word": "you", "start": 233.28, "end": 233.6}, {"word": "hold", "start": 233.6, "end": 233.92}, {"word": "me", "start": 233.92, "end": 234.28}, {"word": "through", "start": 234.28, "end": 234.52}, {"word": "the", "start": 234.52, "end": 234.76}, {"word": "night?", "start": 234.76, "end": 235.2, "stretch": true}]}, {"time": 235.25, "text": "Put your lips all over my", "words": [{"word": "Put", "start": 235.25, "end": 235.83}, {"word": "your", "start": 236.13, "end": 236.33}, {"word": "lips", "start": 236.33, "end": 236.67}, {"word": "all", "start": 236.67, "end": 237.09}, {"word": "over", "start": 237.09, "end": 237.41}, {"word": "my", "start": 237.41, "end": 237.916, "stretch": true}]}, {"time": 237.966, "text": "Salty face when I start cryin'", "words": [{"word": "Salty", "start": 237.966, "end": 238.286}, {"word": "face", "start": 238.286, "end": 239.126}, {"word": "when", "start": 239.126, "end": 239.546}, {"word": "I", "start": 239.546, "end": 239.786}, {"word": "start", "start": 239.786, "end": 240.166}, {"word": "cryin'", "start": 240.166, "end": 242.566, "stretch": true}]}, {"time": 243.22, "text": "Could you be my first time?", "words": [{"word": "Could", "start": 243.22, "end": 243.46}, {"word": "you", "start": 243.46, "end": 243.82}, {"word": "be", "start": 243.82, "end": 244.12}, {"word": "my", "start": 244.12, "end": 244.54}, {"word": "first", "start": 244.54, "end": 244.94}, {"word": "time?", "start": 244.94, "end": 245.37}]}, {"time": 245.42, "text": "Eat me up like apple pie", "words": [{"word": "Eat", "start": 245.42, "end": 246.1}, {"word": "me", "start": 246.46, "end": 246.5}, {"word": "up", "start": 246.5, "end": 247.0}, {"word": "like", "start": 247.0, "end": 247.24}, {"word": "apple", "start": 247.24, "end": 247.58}, {"word": "pie", "start": 247.58, "end": 248.429, "stretch": true}]}, {"time": 248.479, "text": "Make me not wanna die", "words": [{"word": "Make", "start": 248.479, "end": 248.939}, {"word": "me", "start": 248.939, "end": 249.577}, {"word": "not", "start": 249.639, "end": 250.099}, {"word": "wanna", "start": 250.099, "end": 250.579}, {"word": "die", "start": 250.579, "end": 251.089, "stretch": true}]}, {"time": 251.139, "text": "Love me rough and let me fly", "words": [{"word": "Love", "start": 251.139, "end": 251.479}, {"word": "me", "start": 251.479, "end": 251.939}, {"word": "rough", "start": 251.939, "end": 252.239}, {"word": "and", "start": 252.239, "end": 252.559}, {"word": "let", "start": 252.559, "end": 252.779}, {"word": "me", "start": 252.779, "end": 253.259}, {"word": "fly", "start": 253.259, "end": 253.819, "stretch": true}]}, {"time": 253.869, "text": "Get me up, yeah, get me high", "words": [{"word": "Get", "start": 253.869, "end": 254.349}, {"word": "me", "start": 254.349, "end": 254.829}, {"word": "up,", "start": 254.829, "end": 255.109}, {"word": "yeah,", "start": 255.109, "end": 255.249}, {"word": "get", "start": 255.289, "end": 255.629}, {"word": "me", "start": 255.629, "end": 256.089}, {"word": "high", "start": 256.089, "end": 256.129}]}, {"time": 256.179, "text": "Tie me down, don't leave my side", "words": [{"word": "Tie", "start": 256.179, "end": 256.599}, {"word": "me", "start": 256.599, "end": 256.959}, {"word": "down,", "start": 256.959, "end": 257.339}, {"word": "don't", "start": 257.339, "end": 257.639}, {"word": "leave", "start": 257.639, "end": 257.959}, {"word": "my", "start": 257.959, "end": 258.319}, {"word": "side", "start": 258.319, "end": 259.089, "stretch": true}]}, {"time": 259.139, "text": "Don't be a waste of my time", "words": [{"word": "Don't", "start": 259.139, "end": 259.519}, {"word": "be", "start": 259.519, "end": 259.959}, {"word": "a", "start": 259.959, "end": 260.399}, {"word": "waste", "start": 260.399, "end": 260.639}, {"word": "of", "start": 260.639, "end": 260.959}, {"word": "my", "start": 260.959, "end": 261.299}, {"word": "time", "start": 261.299, "end": 262.899, "stretch": true}]}, {"time": 263.74, "text": "Can we just be honest?", "words": [{"word": "Can", "start": 263.74, "end": 264.52}, {"word": "we", "start": 264.52, "end": 264.92}, {"word": "just", "start": 264.92, "end": 265.26}, {"word": "be", "start": 265.26, "end": 265.809}, {"word": "honest?", "start": 266.02, "end": 266.6, "stretch": true}]}, {"time": 266.58, "text": "These are the requirements", "words": [{"word": "These", "start": 266.58, "end": 267.18}, {"word": "are", "start": 267.18, "end": 267.68}, {"word": "the", "start": 267.68, "end": 268.08}, {"word": "requirements", "start": 268.08, "end": 269.02, "stretch": true}]}, {"time": 269.04, "text": "If you think you can be my one and only true love", "words": [{"word": "If", "start": 269.04, "end": 269.599}, {"word": "you", "start": 269.76, "end": 270.1}, {"word": "think", "start": 270.1, "end": 270.34}, {"word": "you", "start": 270.34, "end": 270.62}, {"word": "can", "start": 270.62, "end": 271}, {"word": "be", "start": 271, "end": 271.38}, {"word": "my", "start": 271.38, "end": 271.72}, {"word": "one", "start": 271.72, "end": 271.96}, {"word": "and", "start": 271.96, "end": 272.42}, {"word": "only", "start": 272.42, "end": 272.9}, {"word": "true", "start": 272.9, "end": 273.38}, {"word": "love", "start": 273.38, "end": 274.33, "stretch": true}]}, {"time": 274.38, "text": "You must promise to love me", "words": [{"word": "You", "start": 274.38, "end": 274.88}, {"word": "must", "start": 274.88, "end": 275.18}, {"word": "promise", "start": 275.18, "end": 275.74}, {"word": "to", "start": 275.74, "end": 276.18}, {"word": "love", "start": 276.18, "end": 276.72}, {"word": "me", "start": 276.72, "end": 276.91}]}, {"time": 276.96, "text": "And damn it, if you fuck me over", "words": [{"word": "And", "start": 276.96, "end": 277.5}, {"word": "damn", "start": 277.5, "end": 277.88}, {"word": "it,", "start": 277.88, "end": 278.16}, {"word": "if", "start": 278.16, "end": 278.46}, {"word": "you", "start": 278.46, "end": 278.66}, {"word": "fuck", "start": 278.66, "end": 279.1}, {"word": "me", "start": 279.1, "end": 279.48}, {"word": "over", "start": 279.48, "end": 280.664, "stretch": true}]}, {"time": 280.714, "text": "I will rip your fuckin' face apart", "words": [{"word": "I", "start": 280.714, "end": 281.094}, {"word": "will", "start": 281.094, "end": 281.374}, {"word": "rip", "start": 281.374, "end": 281.714}, {"word": "your", "start": 281.714, "end": 282.094}, {"word": "fuckin'", "start": 282.094, "end": 282.554}, {"word": "face", "start": 282.554, "end": 283.514}, {"word": "apart", "start": 283.514, "end": 285.328, "stretch": true}]}, {"time": 285.378, "text": "High school sweethearts, line up", "words": [{"word": "High", "start": 285.378, "end": 286.178}, {"word": "school", "start": 286.178, "end": 286.578}, {"word": "sweethearts,", "start": 286.578, "end": 287.898}, {"word": "line", "start": 287.898, "end": 288.438}, {"word": "up", "start": 288.438, "end": 288.778}]}, {"time": 288.828, "text": "Not tryna waste my time", "words": [{"word": "Not", "start": 288.828, "end": 289.371}, {"word": "tryna", "start": 289.748, "end": 289.828}, {"word": "waste", "start": 289.828, "end": 290.108}, {"word": "my", "start": 290.108, "end": 290.468}, {"word": "time", "start": 290.468, "end": 290.888, "stretch": true}]}, {"time": 290.938, "text": "High school sweethearts, shut up", "words": [{"word": "High", "start": 290.938, "end": 291.338}, {"word": "school", "start": 291.338, "end": 291.758}, {"word": "sweethearts,", "start": 291.758, "end": 292.178}, {"word": "shut", "start": 292.178, "end": 292.538}, {"word": "up", "start": 292.538, "end": 293.064, "stretch": true}]}, {"time": 294.02, "text": "If you're not my type", "words": [{"word": "If", "start": 294.02, "end": 294.2}, {"word": "you're", "start": 294.2, "end": 294.5}, {"word": "not", "start": 294.5, "end": 294.7}, {"word": "my", "start": 294.7, "end": 295.08}, {"word": "type", "start": 295.08, "end": 295.39, "stretch": true}]}, {"time": 295.44, "text": "High school sweethearts, line up", "words": [{"word": "High", "start": 295.44, "end": 295.72}, {"word": "school", "start": 295.72, "end": 296.24}, {"word": "sweethearts,", "start": 296.24, "end": 296.76}, {"word": "line", "start": 296.76, "end": 297.726}, {"word": "up", "start": 298.32, "end": 298.82, "stretch": true}]}, {"time": 299.06, "text": "Not tryna waste my time", "words": [{"word": "Not", "start": 299.06, "end": 299.16}, {"word": "tryna", "start": 299.16, "end": 299.46}, {"word": "waste", "start": 299.46, "end": 299.78}, {"word": "my", "start": 299.78, "end": 300.16}, {"word": "time", "start": 300.16, "end": 300.26}]}, {"time": 300.31, "text": "High school sweethearts, shut up", "words": [{"word": "High", "start": 300.31, "end": 300.69}, {"word": "school", "start": 300.69, "end": 301.11}, {"word": "sweethearts,", "start": 301.11, "end": 301.57}, {"word": "shut", "start": 301.57, "end": 301.93}, {"word": "up", "start": 301.93, "end": 302.49, "stretch": true}]}, {"time": 304.2, "text": "If you're not my type", "words": [{"word": "If", "start": 304.2, "end": 304.38}, {"word": "you're", "start": 304.38, "end": 304.62}, {"word": "not", "start": 304.62, "end": 304.84}, {"word": "my", "start": 304.84, "end": 305.24}, {"word": "type", "start": 305.24, "end": 305.64}]}]